lightweight_charts_pro/__init__.py
lightweight_charts_pro/logging_config.py
lightweight_charts_pro/charts/__init__.py
lightweight_charts_pro/charts/base_chart.py
lightweight_charts_pro/charts/base_chart_manager.py
lightweight_charts_pro/charts/managers/__init__.py
lightweight_charts_pro/charts/managers/price_scale_manager.py
lightweight_charts_pro/charts/managers/series_manager.py
lightweight_charts_pro/charts/managers/trade_manager.py
lightweight_charts_pro/charts/options/__init__.py
lightweight_charts_pro/charts/options/base_options.py
lightweight_charts_pro/charts/options/chart_options.py
lightweight_charts_pro/charts/options/interaction_options.py
lightweight_charts_pro/charts/options/layout_options.py
lightweight_charts_pro/charts/options/line_options.py
lightweight_charts_pro/charts/options/localization_options.py
lightweight_charts_pro/charts/options/price_format_options.py
lightweight_charts_pro/charts/options/price_line_options.py
lightweight_charts_pro/charts/options/price_scale_options.py
lightweight_charts_pro/charts/options/sync_options.py
lightweight_charts_pro/charts/options/time_scale_options.py
lightweight_charts_pro/charts/options/trade_visualization_options.py
lightweight_charts_pro/charts/options/ui_options.py
lightweight_charts_pro/charts/series/__init__.py
lightweight_charts_pro/charts/series/area.py
lightweight_charts_pro/charts/series/band.py
lightweight_charts_pro/charts/series/bar_series.py
lightweight_charts_pro/charts/series/base.py
lightweight_charts_pro/charts/series/baseline.py
lightweight_charts_pro/charts/series/candlestick.py
lightweight_charts_pro/charts/series/defaults.py
lightweight_charts_pro/charts/series/gradient_ribbon.py
lightweight_charts_pro/charts/series/histogram.py
lightweight_charts_pro/charts/series/line.py
lightweight_charts_pro/charts/series/ribbon.py
lightweight_charts_pro/charts/series/signal_series.py
lightweight_charts_pro/charts/series/trend_fill.py
lightweight_charts_pro/charts/utils/__init__.py
lightweight_charts_pro-0.1.0.dist-info/licenses/LICENSE
lightweight_charts_pro-0.1.0.dist-info/METADATA
lightweight_charts_pro-0.1.0.dist-info/WHEEL
lightweight_charts_pro-0.1.0.dist-info/top_level.txt
lightweight_charts_pro-0.1.0.dist-info/RECORD
