Metadata-Version: 2.4
Name: lightweight-charts-pro
Version: 0.1.0
Summary: Framework-agnostic Python core library for TradingView Lightweight Charts Pro
Author: Streamlit Lightweight Charts Contributors
License: MIT
Project-URL: Homepage, https://github.com/nandkapadia/streamlit-lightweight-charts-pro
Project-URL: Documentation, https://github.com/nandkapadia/streamlit-lightweight-charts-pro#readme
Project-URL: Repository, https://github.com/nandkapadia/streamlit-lightweight-charts-pro.git
Keywords: lightweight-charts,tradingview,charts,financial,trading,python
Classifier: Development Status :: 4 - Beta
Classifier: Intended Audience :: Developers
Classifier: License :: OSI Approved :: MIT License
Classifier: Programming Language :: Python :: 3
Classifier: Programming Language :: Python :: 3.10
Classifier: Programming Language :: Python :: 3.11
Classifier: Programming Language :: Python :: 3.12
Classifier: Topic :: Scientific/Engineering :: Visualization
Requires-Python: >=3.10
License-File: LICENSE
Requires-Dist: pandas>=2.0.0
Requires-Dist: numpy>=1.24.0
Provides-Extra: dev
Requires-Dist: pytest>=7.0.0; extra == "dev"
Requires-Dist: pytest-cov>=4.0.0; extra == "dev"
Requires-Dist: mypy>=1.0.0; extra == "dev"
Requires-Dist: ruff>=0.1.0; extra == "dev"
Dynamic: license-file
